dolphin/__init__.py
dolphin/memorylib.py
sup_dolphin_memory_lib-0.1.2.dist-info/LICENSE
sup_dolphin_memory_lib-0.1.2.dist-info/METADATA
sup_dolphin_memory_lib-0.1.2.dist-info/WHEEL
sup_dolphin_memory_lib-0.1.2.dist-info/top_level.txt
sup_dolphin_memory_lib-0.1.2.dist-info/RECORD
